safe_syslog_handler/__init__.py
safe_syslog_handler/handlers.py
safe_syslog_handler-0.2.0.dist-info/DESCRIPTION.rst
safe_syslog_handler-0.2.0.dist-info/METADATA
safe_syslog_handler-0.2.0.dist-info/RECORD
safe_syslog_handler-0.2.0.dist-info/WHEEL
safe_syslog_handler-0.2.0.dist-info/metadata.json
safe_syslog_handler-0.2.0.dist-info/top_level.txt
