Metadata-Version: 2.0
Name: safe-syslog-handler
Version: 0.2.0
Summary: SafeSysLogHandler recreates the connection to a remote logging server when the connection is lost, avoiding the `[errno 32] Broken Pipe` error which would occur when using the `SysLogHandler`.
Home-page: https://github.com/intelie/safe_syslog_handler
Author: Felipe Arruda Pontes
Author-email: felipe.arruda@intelie.com.br
License: Apache Software License 2.0
Keywords: safe SysLogHandler broken pipe errno32
Platform: UNKNOWN
Classifier: Development Status :: 4 - Beta
Classifier: Intended Audience :: Developers
Classifier: License :: OSI Approved :: Apache Software License
Classifier: Topic :: System :: Logging
Classifier: Natural Language :: English
Classifier: Programming Language :: Python :: 2
Classifier: Programming Language :: Python :: 2.7
Classifier: Programming Language :: Python :: 3
Classifier: Programming Language :: Python :: 3.3
Classifier: Programming Language :: Python :: 3.4
Classifier: Programming Language :: Python :: 3.5
Classifier: Programming Language :: Python :: 3.6
Classifier: Programming Language :: Python :: 3.7
